getnum/__init__.py
getnum/getnum.py
getnum-1.0.3.dist-info/METADATA
getnum-1.0.3.dist-info/WHEEL
getnum-1.0.3.dist-info/top_level.txt
getnum-1.0.3.dist-info/RECORD
